pylttb
