Metadata-Version: 1.0
Name: pylttb
Version: 0.1.9
Summary: pylttb - downsampling of given series using Largest Triangle Three Buckets method.
Home-page: UNKNOWN
Author: Konrad Jałowiecki <dexter2206@gmail.com>
Author-email: dexter2206@gmail.com
License: MIT
Keywords: downsampling largest triangle three buckets
Platform: Linux
Platform: Unix
